{
  "es": {
    "schedule": {
      "day": "Día",
      "week": "Semana",
      "workWeek": "laborables",
      "month": "Mes",
      "agenda": "Agenda",
      "weekAgenda": "Agenda semanal",
      "workWeekAgenda": "Agenda semana laboral",
      "monthAgenda": "Agenda mensual",
      "today": "Hoy",
      "noEvents": "No hay eventos",
      "emptyContainer": "No existen eventos programados para este día.",
      "allDay": "Todo el día",
      "start": "Comienzo",
      "end": "Fin",
      "more": "Más",
      "close": "Cerrar",
      "cancel": "Cancelar",
      "noTitle": "(Sin Título)",
      "delete": "Eliminar",
      "deleteEvent": "Eliminar Evento",
      "deleteMultipleEvent": "Eliminar Multiples Eventos",
      "selectedItems": "Elementos Seleccionados",
      "deleteSeries": "Eliminar la Serie",
      "edit": "Modificar",
      "editSeries": "Modificar Serie",
      "editEvent": "Modificar Evento",
      "createEvent": "Añadir",
      "subject": "Asunto",
      "addTitle": "Añadir Título",
      "moreDetails": "Más Detalles",
      "save": "Guardar",
      "editContent": "Do you want to edit only this event or entire series?",
      "deleteRecurrenceContent": "Do you want to delete only this event or entire series?",
      "deleteContent": "Are you sure you want to delete this event?",
      "deleteMultipleContent": "Are you sure you want to delete the selected events?",
      "newEvent": "Nuevo Evento",
      "title": "Título",
      "location": "Ubicación",
      "description": "Descripción",
      "timezone": "Timezone",
      "startTimezone": "Start Timezone",
      "endTimezone": "End Timezone",
      "repeat": "Repetir",
      "saveButton": "Guardar",
      "cancelButton": "Cancelar",
      "deleteButton": "Eliminar",
      "recurrence": "Recurrencia",
      "wrongPattern": "The recurrence pattern is not valid.",
      "seriesChangeAlert": "The changes made to specific instances of this series will be cancelled and those events will match the series again.",
      "createError": "The duration of the event must be shorter than how frequently it occurs. Shorten the duration, or change the recurrence pattern in the recurrence event editor.",
      "recurrenceDateValidation": "Some months have fewer than the selected date. For these months, the occurrence will fall on the last date of the month.",
      "sameDayAlert": "Two occurrences of the same event cannot occur on the same day.",
      "editRecurrence": "Edit Recurrence",
      "repeats": "Repeticiones",
      "alert": "Alerta",
      "startEndError": "The selected end date occurs before the start date.",
      "invalidDateError": "The entered date value is invalid.",
      "ok": "Ok",
      "occurrence": "Occurrence",
      "series": "Series",
      "previous": "Anterior",
      "next": "Siguiente",
      "timelineDay": "Timeline Day",
      "timelineWeek": "Timeline Week",
      "timelineWorkWeek": "Timeline Work Week",
      "timelineMonth": "Timeline Month"      
    },
    "recurrenceeditor": {
      "none": "None",
      "daily": "Diario",
      "weekly": "Semanal",
      "monthly": "Mensual",
      "month": "Mes",
      "yearly": "Anual",
      "never": "Nunca",
      "until": "hasta",
      "count": "Count",
      "first": "Primero",
      "second": "Segundo",
      "third": "Tercero",
      "fourth": "Cuarto",
      "last": "Last",
      "repeat": "Repetir",
      "repeatEvery": "Repetir Cada",
      "on": "Repeat On",
      "end": "Fin",
      "onDay": "Día",
      "days": "Day(s)",
      "weeks": "Week(s)",
      "months": "Month(s)",
      "years": "Year(s)",
      "every": "Todos los",
      "summaryTimes": "time(s)",
      "summaryOn": "on",
      "summaryUntil": "until",
      "summaryRepeat": "Repeats",
      "summaryDay": "día(s)",
      "summaryWeek": "week(s)",
      "summaryMonth": "month(s)",
      "summaryYear": "year(s)"
    },
    "calendar": {
      "today": "hoy"
    },
    "datetimepicker": { 
      "today": "hoy" 
    }    
  }
}